pyraug/__init__.py
pyraug/config.py
pyraug/customexception.py
pyraug/data/__init__.py
pyraug/data/datasets.py
pyraug/data/loaders.py
pyraug/data/preprocessors.py
pyraug/models/__init__.py
pyraug/models/base/__init__.py
pyraug/models/base/base_config.py
pyraug/models/base/base_sampler.py
pyraug/models/base/base_utils.py
pyraug/models/base/base_vae.py
pyraug/models/nn/__init__.py
pyraug/models/nn/base_architectures.py
pyraug/models/nn/default_architectures.py
pyraug/models/rhvae/__init__.py
pyraug/models/rhvae/rhvae_config.py
pyraug/models/rhvae/rhvae_model.py
pyraug/models/rhvae/rhvae_sampler.py
pyraug/models/rhvae/rhvae_utils.py
pyraug/pipelines/__init__.py
pyraug/pipelines/base_pipeline.py
pyraug/pipelines/generation.py
pyraug/pipelines/pipeline_utils.py
pyraug/pipelines/training.py
pyraug/trainers/__init__.py
pyraug/trainers/trainer_utils.py
pyraug/trainers/trainers.py
pyraug/trainers/training_config.py
pyraug-0.0.6.dist-info/LICENSE
pyraug-0.0.6.dist-info/METADATA
pyraug-0.0.6.dist-info/WHEEL
pyraug-0.0.6.dist-info/top_level.txt
pyraug-0.0.6.dist-info/RECORD
