Metadata-Version: 2.1
Name: pyraug
Version: 0.0.6
Summary: Data Augmentation with VAE
Home-page: https://github.com/clementchadebec/pyraug
Author: Clement Chadebec (HekA team INRIA)
Author-email: clement.chadebec@inria.fr
License: UNKNOWN
Project-URL: Bug Tracker, https://github.com/clementchadebec/pyraug/issues
Platform: UNKNOWN
Classifier: Programming Language :: Python :: 3
Classifier: Programming Language :: Python :: 3.6
Classifier: Programming Language :: Python :: 3.7
Classifier: Programming Language :: Python :: 3.8
Classifier: License :: OSI Approved :: Apache Software License
Classifier: Operating System :: OS Independent
Requires-Python: >=3.6
License-File: LICENSE
Requires-Dist: numpy (>=1.22.0)
Requires-Dist: Pillow (>=8.3.2)
Requires-Dist: torch (>=1.8.1)
Requires-Dist: dill (>=0.3.3)
Requires-Dist: nibabel (>=3.2.1)
Requires-Dist: pydantic (>=1.8.2)
Requires-Dist: dataclasses (>=0.6)
